dbastable/__init__.py
dbastable/_broadcaster.py
dbastable/_def.py
dbastable/_sanitizer.py
dbastable/_sqldb.py
dbastable/_viewers.py
dbastable/version.py
dbastable/where.py
dbastable/tests/__init__.py
dbastable/tests/mixins.py
dbastable/tests/test_broadcaster.py
dbastable/tests/test_db.py
dbastable/tests/test_non_conformant_columns.py
dbastable/tests/test_sanitizer.py
dbastable/tests/test_viewers.py
dbastable/tests/test_where.py
dbastable-0.5.dev1.dist-info/LICENSE
dbastable-0.5.dev1.dist-info/METADATA
dbastable-0.5.dev1.dist-info/WHEEL
dbastable-0.5.dev1.dist-info/top_level.txt
dbastable-0.5.dev1.dist-info/RECORD
