Metadata-Version: 2.1
Name: dbastable
Version: 0.5.dev1
Summary: The easiest way to work with simple SQLite tables.
Author-email: Julio Campagnolo <juliocampagnolo@gmail.com>
License: MIT License
Project-URL: Homepage, https://github.com/juliotux/dbastable
Project-URL: Issues, https://github.com/juliotux/dbastable/issues
Project-URL: Source, https://github.com/juliotux/dbastable
Project-URL: Documentation, https://dbastable.readthedocs.io/en/latest/
License-File: LICENSE
Requires-Dist: numpy
Provides-Extra: docs
Requires-Dist: sphinx ; extra == 'docs'
Requires-Dist: pydata-sphinx-theme ; extra == 'docs'
Requires-Dist: sphinx-automodapi ; extra == 'docs'
Requires-Dist: numpydoc ; extra == 'docs'
Provides-Extra: test
Requires-Dist: coverage ; extra == 'test'
Requires-Dist: astropy ; extra == 'test'
